arcaflow/__init__.py
arcaflow/arcaflow.py
arcaflow/engineargs.py
arcaflow/bin/arcaflow
arcaflow-0.20.0.dist-info/LICENSE
arcaflow-0.20.0.dist-info/METADATA
arcaflow-0.20.0.dist-info/WHEEL
arcaflow-0.20.0.dist-info/top_level.txt
arcaflow-0.20.0.dist-info/RECORD
