Metadata-Version: 2.1
Name: arcaflow
Version: 0.20.0
Summary: Arcaflow engine python wrapper
Home-page: https://arcalot.io/arcaflow/
Author: Arcalot Contributors
License: Apache
Platform: UNKNOWN
License-File: LICENSE
